osdu/__init__.py
osdu/utils.py
osdu/client/__init__.py
osdu/client/_base.py
osdu/client/_service_principal_util.py
osdu/client/aws.py
osdu/client/aws_service_principal.py
osdu/client/simple.py
osdu/services/__init__.py
osdu/services/base.py
osdu/services/dataset.py
osdu/services/entitlements.py
osdu/services/search.py
osdu/services/storage.py
tests/__init__.py
tests/integration.py
tests/unit.py
osdupy-0.4.0.dist-info/LICENSE
osdupy-0.4.0.dist-info/METADATA
osdupy-0.4.0.dist-info/WHEEL
osdupy-0.4.0.dist-info/top_level.txt
osdupy-0.4.0.dist-info/RECORD
