Metadata-Version: 2.1
Name: osdupy
Version: 0.4.0
Summary: A simple python client for interacting with the OSDU API.
Home-page: https://github.com/pariveda/osdupy
Author: Pariveda Solutions, Inc.
Author-email: mike.duffy@parivedasolutions.com
License: UNKNOWN
Platform: UNKNOWN
Classifier: Programming Language :: Python :: 3
Classifier: License :: OSI Approved :: MIT License
Classifier: Operating System :: OS Independent
Requires-Python: >=3.6
License-File: LICENSE
